{
    "id":116352,
    "corpusName":"LCC",
    "corpusId":99,
    "name":"1017_tekstas.txt",
    "comment":"",
    "dateCreated":"2018-12-07T12:49:02.270+02:00",
    "dateModified":"2019-11-07T18:39:47.298+02:00",
    "content":"(papildyta 09.56 val.) Gruzija ir Moldova penktadienį parafavo asociacijos ir laisvos prekybos sutartis su Europos Sąjunga (ES). Tačiau Ukraina atsisakė pasirašyti Asociacijos sutartį. Ukrainos vadovas Viktoras Janukovyčius savo nuomonės penktadienį nepakeitė.\nŠalies Prezidentė Dalia Grybauskaitė penktadienį prieš antrą ES viršūnių susitikimo dieną išreiškė savo nusivylimą Ukrainos vadovybe. Pasak jos, Ukrainos vadovų sprendimas nepasirašyti su ES Asociacijos sutarties stabdo progresą šalyje. Toks kelias, pasak šalies vadovės, veda niekur.\nES vadovai penktadienį tęs diskusijas su Ukrainos prezidentu V. Janukovičiumi apie Ukrainos ateitį. „Vakar status quo nepasikeitė. Ukrainos prezidentas nebuvo pasirengęs žengti kitą žingsnį integracijoje su ES“, - teigė D. Grybauskaitė.\nPasak Prezidentės, ši situacija gali pasikeisti tik tuo atveju, jei dabartinė Ukrainos vadovybė padarytų galutinį sprendimą, ar verta integruotis ir link Vakarų. „Ukrainos žmonės savo nuomonę išsako, mes žinome apklausų duomenis, kad daugiau nei 60 proc. Ukrainos žmonių norėtų suartėjimo su Vakarais. Deja to mes nematome iš dabartinės Ukrainos vyriausybės“, - tvirtina Prezidentė.\nD. Grybauskaitė taip pat pareiškė, kad labiausiai dėl Asociacijos sutarties nepasirašymo nusivylę turėtų būti Ukrainos žmonės. „Šiandien Ukrainos vadovybė pasirenka kelią, kuris veda niekur“, - pareiškė ji.\nPrezidentė šiame proceso ES pralaimėjimo neįžvelgia. Ji tvirtina, kad labiausiai dėl tokio sprendimo kenčia pati Ukraina: „Aš matau pralaimėjimą Ukrainos. Toks apsisprendimas, kurį dabar demonstruoja Ukrainos vadovai, reiškia Ukrainos žmonių galimybių apribojimą siekti geresnio gyvenimo, gyventi demokratinėje valstybėje. Tai yra dabartinės Ukrainos vadovybės apsisprendimas - sustabdyti progresą savo šalyje.“\nAntroji ES viršūnių susitikimo Vilniuje diena taip pat bus skirta sutarčių pasirašymams su Rytų partnerystės valstybėmis. Bus pasirašyti susitarimai su Gruzija, Moldova ir Azerbaidžanu. Nuo kitų metų pradžios Moldovai bus suteiktas visiškas bevizis režimas.\n„Tai yra labai apčiuopiami rezultatai šios partnerystės po ketverių metų. Ir labai džiaugiuosi ir sveikinu tas šalis, kurios yra pasirengusios, padariusius daug namų darbų, tai yra ypač Moldovą ir Gruziją, su šiais pasiekimais“, - penktadienį kalbėjo šalies vadovė.",
    "source":"",
    "url":"http://archive.ph/6x88I",
    "lexemeCount":0,
    "tags":[
    ],
    "annotationLayers":[
        {
            "id":1366073,
            "type":"manualCoreferences",
            "version":5,
            "dateCreated":"2019-05-28T16:11:59.940+03:00",
            "dateModified":"2019-05-28T16:11:59.940+03:00",
            "content":"{\"coreferences\":[{\"Mentions\":[[279,18]],\"Referant\":[401,3],\"Type\":\"poas\"},{\"Mentions\":[[1331,5]],\"Referant\":[1338,5],\"Type\":\"peas\"},{\"Mentions\":[[1166,15]],\"Referant\":[1369,2],\"Type\":\"ppas\"},{\"Mentions\":[[1373,10]],\"Referant\":[1426,2],\"Type\":\"ppas\"},{\"Mentions\":[[1533,14]],\"Referant\":[1549,4],\"Type\":\"peas\"},{\"Mentions\":[[2154,5]],\"Referant\":[2161,6],\"Type\":\"peas\"},{\"Mentions\":[[136,7]],\"Referant\":[185,8],\"Type\":\"dtis\"},{\"Mentions\":[[107,15]],\"Referant\":[322,2],\"Type\":\"dbis\"},{\"Mentions\":[[136,7]],\"Referant\":[376,8],\"Type\":\"dtis\"},{\"Mentions\":[[136,7]],\"Referant\":[406,8],\"Type\":\"dtis\"},{\"Mentions\":[[107,15]],\"Referant\":[449,2],\"Type\":\"dtis\"},{\"Mentions\":[[107,15]],\"Referant\":[546,2],\"Type\":\"dtis\"},{\"Mentions\":[[136,7]],\"Referant\":[587,8],\"Type\":\"dtis\"},{\"Mentions\":[[136,7]],\"Referant\":[629,8],\"Type\":\"dtis\"},{\"Mentions\":[[136,7]],\"Referant\":[677,8],\"Type\":\"dtis\"},{\"Mentions\":[[107,15]],\"Referant\":[753,2],\"Type\":\"dbis\"},{\"Mentions\":[[279,18]],\"Referant\":[766,15],\"Type\":\"dbis\"},{\"Mentions\":[[136,7]],\"Referant\":[861,8],\"Type\":\"dtis\"},{\"Mentions\":[[136,7]],\"Referant\":[946,8],\"Type\":\"dtis\"},{\"Mentions\":[[136,7]],\"Referant\":[1038,8],\"Type\":\"dtis\"},{\"Mentions\":[[136,7]],\"Referant\":[1120,8],\"Type\":\"dtis\"},{\"Mentions\":[[279,18]],\"Referant\":[1166,15],\"Type\":\"dbis\"},{\"Mentions\":[[136,7]],\"Referant\":[1276,8],\"Type\":\"dtis\"},{\"Mentions\":[[136,7]],\"Referant\":[1303,8],\"Type\":\"dtis\"},{\"Mentions\":[[107,15]],\"Referant\":[1398,2],\"Type\":\"dbis\"},{\"Mentions\":[[136,7]],\"Referant\":[1486,7],\"Type\":\"dtis\"},{\"Mentions\":[[136,7]],\"Referant\":[1518,8],\"Type\":\"dtis\"},{\"Mentions\":[[136,7]],\"Referant\":[1573,8],\"Type\":\"dtis\"},{\"Mentions\":[[136,7]],\"Referant\":[1599,8],\"Type\":\"dtis\"},{\"Mentions\":[[136,7]],\"Referant\":[1715,8],\"Type\":\"dtis\"},{\"Mentions\":[[753,2]],\"Referant\":[1793,2],\"Type\":\"dtis\"},{\"Mentions\":[[23,7]],\"Referant\":[1937,7],\"Type\":\"dtis\"},{\"Mentions\":[[34,7]],\"Referant\":[1946,7],\"Type\":\"dtis\"},{\"Mentions\":[[34,7]],\"Referant\":[1994,8],\"Type\":\"dtis\"},{\"Mentions\":[[34,7]],\"Referant\":[2229,7],\"Type\":\"dtis\"},{\"Mentions\":[[23,7]],\"Referant\":[2240,7],\"Type\":\"dtis\"},{\"Mentions\":[[1373,10]],\"Referant\":[1496,2],\"Type\":\"ppas\"},{\"Mentions\":[[607,16]],\"Referant\":[686,11],\"Type\":\"gfas\"},{\"Mentions\":[[202,21]],\"Referant\":[607,16],\"Type\":\"dbis\"},{\"Mentions\":[[766,15]],\"Referant\":[789,11],\"Type\":\"gfas\"},{\"Mentions\":[[766,15]],\"Referant\":[1154,10],\"Type\":\"gfas\"},{\"Mentions\":[[1166,15]],\"Referant\":[1373,10],\"Type\":\"gfas\"},{\"Mentions\":[],\"Referant\":[1373,10],\"Type\":\"ghps\"},{\"Mentions\":[[279,18]],\"Referant\":[360,4],\"Type\":\"poas\"}]}",
            "tags":[
            ]
        },
        {
            "id":1365918,
            "type":"manualCoreferences",
            "version":4,
            "dateCreated":"2019-05-01T12:54:52.225+03:00",
            "dateModified":"2019-05-01T12:54:52.225+03:00",
            "content":"{\"coreferences\":[{\"Mentions\":[[279,18]],\"Referant\":[401,3],\"Type\":\"poas\"},{\"Mentions\":[[1331,5]],\"Referant\":[1338,5],\"Type\":\"peas\"},{\"Mentions\":[[1166,15]],\"Referant\":[1369,2],\"Type\":\"ppas\"},{\"Mentions\":[[1373,10]],\"Referant\":[1426,2],\"Type\":\"ppas\"},{\"Mentions\":[[1533,14]],\"Referant\":[1549,4],\"Type\":\"peas\"},{\"Mentions\":[[2154,5]],\"Referant\":[2161,6],\"Type\":\"peas\"},{\"Mentions\":[[107,15]],\"Referant\":[322,2],\"Type\":\"dbis\"},{\"Mentions\":[[107,15]],\"Referant\":[753,2],\"Type\":\"dbis\"},{\"Mentions\":[[279,18]],\"Referant\":[766,15],\"Type\":\"dbis\"},{\"Mentions\":[[279,18]],\"Referant\":[1166,15],\"Type\":\"dbis\"},{\"Mentions\":[[107,15]],\"Referant\":[1398,2],\"Type\":\"dbis\"},{\"Mentions\":[[1518,8],[136,7]],\"Referant\":[1486,7],\"Type\":\"dtig\"},{\"Mentions\":[[1373,10]],\"Referant\":[1496,2],\"Type\":\"ppas\"},{\"Mentions\":[[279,18]],\"Referant\":[524,7],\"Type\":\"gfas\"},{\"Mentions\":[[607,16]],\"Referant\":[686,11],\"Type\":\"gfas\"},{\"Mentions\":[[202,21]],\"Referant\":[607,16],\"Type\":\"dbis\"},{\"Mentions\":[[766,15]],\"Referant\":[789,11],\"Type\":\"gfas\"},{\"Mentions\":[[870,8]],\"Referant\":[1129,11],\"Type\":\"gsis\"},{\"Mentions\":[[766,15]],\"Referant\":[1154,10],\"Type\":\"gfas\"},{\"Mentions\":[[1129,11]],\"Referant\":[1582,7],\"Type\":\"gsas\"},{\"Mentions\":[[1166,15]],\"Referant\":[1373,10],\"Type\":\"gfas\"},{\"Mentions\":[],\"Referant\":[1373,10],\"Type\":\"ghps\"},{\"Mentions\":[[164,19]],\"Referant\":[452,21],\"Type\":\"dtis\"},{\"Mentions\":[[1373,10]],\"Referant\":[2301,6],\"Type\":\"gsis\"},{\"Mentions\":[[164,19]],\"Referant\":[1220,21],\"Type\":\"dtis\"},{\"Mentions\":[[279,18]],\"Referant\":[360,4],\"Type\":\"poas\"},{\"Mentions\":[[202,21]],\"Referant\":[224,4],\"Type\":\"poas\"},{\"Mentions\":[[136,7]],\"Referant\":[385,8],\"Type\":\"gmis\"},{\"Mentions\":[[1312,8],[385,8]],\"Referant\":[870,8],\"Type\":\"gtig\"},{\"Mentions\":[[955,6]],\"Referant\":[962,4],\"Type\":\"poas\"},{\"Mentions\":[[1285,6],[955,6]],\"Referant\":[1047,6],\"Type\":\"gtig\"},{\"Mentions\":[[1518,8]],\"Referant\":[1684,10],\"Type\":\"gmis\"},{\"Mentions\":[[1937,7]],\"Referant\":[23,7],\"Type\":\"dtis\"},{\"Mentions\":[[1946,7]],\"Referant\":[34,7],\"Type\":\"dtis\"},{\"Mentions\":[[1724,9]],\"Referant\":[1771,4],\"Type\":\"poas\"},{\"Mentions\":[[1957,12],[1946,7],[1937,7]],\"Referant\":[1894,11],\"Type\":\"gfpg\"},{\"Mentions\":[[2240,7],[2229,7]],\"Referant\":[2154,5],\"Type\":\"gfpg\"},{\"Mentions\":[[2240,7]],\"Referant\":[1937,7],\"Type\":\"dtis\"},{\"Mentions\":[[1994,8]],\"Referant\":[1946,7],\"Type\":\"dtis\"},{\"Mentions\":[[2229,7]],\"Referant\":[1994,8],\"Type\":\"dtis\"},{\"Mentions\":[[1486,7]],\"Referant\":[1481,4],\"Type\":\"prps\"}]}",
            "tags":[
            ]
        },
        {
            "id":1365630,
            "type":"manualCoreferences",
            "version":1,
            "dateCreated":"2019-03-05T19:39:17.395+02:00",
            "dateModified":"2019-03-05T19:39:17.395+02:00",
            "content":"{\"coreferences\":[{\"Mentions\":[[279,18]],\"Referant\":[401,3],\"Type\":\"poas\"},{\"Mentions\":[[1331,5]],\"Referant\":[1338,5],\"Type\":\"peas\"},{\"Mentions\":[[1166,15]],\"Referant\":[1369,2],\"Type\":\"ppas\"},{\"Mentions\":[[1373,10]],\"Referant\":[1426,2],\"Type\":\"ppas\"},{\"Mentions\":[[1533,14]],\"Referant\":[1549,4],\"Type\":\"peas\"},{\"Mentions\":[[2154,5]],\"Referant\":[2161,6],\"Type\":\"peas\"},{\"Mentions\":[[136,7]],\"Referant\":[185,8],\"Type\":\"dtis\"},{\"Mentions\":[[107,15]],\"Referant\":[322,2],\"Type\":\"dbis\"},{\"Mentions\":[[136,7]],\"Referant\":[376,8],\"Type\":\"dtis\"},{\"Mentions\":[[136,7]],\"Referant\":[406,8],\"Type\":\"dtis\"},{\"Mentions\":[[107,15]],\"Referant\":[449,2],\"Type\":\"dtis\"},{\"Mentions\":[[107,15]],\"Referant\":[546,2],\"Type\":\"dtis\"},{\"Mentions\":[[136,7]],\"Referant\":[587,8],\"Type\":\"dtis\"},{\"Mentions\":[[136,7]],\"Referant\":[629,8],\"Type\":\"dtis\"},{\"Mentions\":[[136,7]],\"Referant\":[677,8],\"Type\":\"dtis\"},{\"Mentions\":[[107,15]],\"Referant\":[753,2],\"Type\":\"dbis\"},{\"Mentions\":[[279,18]],\"Referant\":[766,15],\"Type\":\"dbis\"},{\"Mentions\":[[136,7]],\"Referant\":[861,8],\"Type\":\"dtis\"},{\"Mentions\":[[136,7]],\"Referant\":[946,8],\"Type\":\"dtis\"},{\"Mentions\":[[136,7]],\"Referant\":[1038,8],\"Type\":\"dtis\"},{\"Mentions\":[[136,7]],\"Referant\":[1120,8],\"Type\":\"dtis\"},{\"Mentions\":[[279,18]],\"Referant\":[1166,15],\"Type\":\"dbis\"},{\"Mentions\":[[136,7]],\"Referant\":[1276,8],\"Type\":\"dtis\"},{\"Mentions\":[[136,7]],\"Referant\":[1303,8],\"Type\":\"dtis\"},{\"Mentions\":[[107,15]],\"Referant\":[1398,2],\"Type\":\"dbis\"},{\"Mentions\":[[136,7]],\"Referant\":[1486,7],\"Type\":\"dtis\"},{\"Mentions\":[[136,7]],\"Referant\":[1518,8],\"Type\":\"dtis\"},{\"Mentions\":[[136,7]],\"Referant\":[1573,8],\"Type\":\"dtis\"},{\"Mentions\":[[136,7]],\"Referant\":[1599,8],\"Type\":\"dtis\"},{\"Mentions\":[[136,7]],\"Referant\":[1715,8],\"Type\":\"dtis\"},{\"Mentions\":[[753,2]],\"Referant\":[1793,2],\"Type\":\"dtis\"},{\"Mentions\":[[23,7]],\"Referant\":[1937,7],\"Type\":\"dtis\"},{\"Mentions\":[[34,7]],\"Referant\":[1946,7],\"Type\":\"dtis\"},{\"Mentions\":[[34,7]],\"Referant\":[1994,8],\"Type\":\"dtis\"},{\"Mentions\":[[34,7]],\"Referant\":[2229,7],\"Type\":\"dtis\"},{\"Mentions\":[[23,7]],\"Referant\":[2240,7],\"Type\":\"dtis\"},{\"Mentions\":[[1373,10]],\"Referant\":[1496,2],\"Type\":\"ppas\"},{\"Mentions\":[[385,8]],\"Referant\":[415,6],\"Type\":\"gsis\"},{\"Mentions\":[[279,18]],\"Referant\":[524,7],\"Type\":\"gfas\"},{\"Mentions\":[[607,16]],\"Referant\":[686,11],\"Type\":\"gfas\"},{\"Mentions\":[[202,21]],\"Referant\":[607,16],\"Type\":\"dbis\"},{\"Mentions\":[[766,15]],\"Referant\":[789,11],\"Type\":\"gfas\"},{\"Mentions\":[[415,6]],\"Referant\":[870,8],\"Type\":\"gsis\"},{\"Mentions\":[[870,8]],\"Referant\":[1129,11],\"Type\":\"gmis\"},{\"Mentions\":[[766,15]],\"Referant\":[1154,10],\"Type\":\"gfas\"},{\"Mentions\":[[1129,11]],\"Referant\":[1582,7],\"Type\":\"gmas\"},{\"Mentions\":[[1166,15]],\"Referant\":[1373,10],\"Type\":\"gfas\"},{\"Mentions\":[],\"Referant\":[1373,10],\"Type\":\"ghps\"},{\"Mentions\":[[164,19]],\"Referant\":[452,21],\"Type\":\"dtis\"},{\"Mentions\":[[1373,10]],\"Referant\":[2301,6],\"Type\":\"gsas\"},{\"Mentions\":[[164,19]],\"Referant\":[1220,21],\"Type\":\"dtis\"},{\"Mentions\":[[385,8]],\"Referant\":[1312,8],\"Type\":\"gtis\"},{\"Mentions\":[[385,8]],\"Referant\":[1724,9],\"Type\":\"gtis\"},{\"Mentions\":[[1957,12],[1946,7],[1937,7]],\"Referant\":[1894,11],\"Type\":\"gfpg\"},{\"Mentions\":[[1486,7]],\"Referant\":[1776,6],\"Type\":\"gfas\"},{\"Mentions\":[[279,18]],\"Referant\":[360,4],\"Type\":\"poas\"}]}",
            "tags":[
            ]
        },
        {
            "id":1365805,
            "type":"manualCoreferences",
            "version":3,
            "dateCreated":"2019-04-04T13:48:28.661+03:00",
            "dateModified":"2019-04-04T13:48:28.661+03:00",
            "content":"{\"coreferences\":[{\"Mentions\":[[279,18]],\"Referant\":[401,3],\"Type\":\"pras\"},{\"Mentions\":[[1331,5]],\"Referant\":[1338,5],\"Type\":\"peas\"},{\"Mentions\":[[1166,15]],\"Referant\":[1369,2],\"Type\":\"pras\"},{\"Mentions\":[[1373,10]],\"Referant\":[1426,2],\"Type\":\"pras\"},{\"Mentions\":[[1533,14]],\"Referant\":[1549,4],\"Type\":\"peas\"},{\"Mentions\":[[2154,5]],\"Referant\":[2161,6],\"Type\":\"peas\"},{\"Mentions\":[[136,7]],\"Referant\":[185,8],\"Type\":\"dtis\"},{\"Mentions\":[[124,2]],\"Referant\":[322,2],\"Type\":\"dtis\"},{\"Mentions\":[[136,7]],\"Referant\":[376,8],\"Type\":\"dtis\"},{\"Mentions\":[[136,7]],\"Referant\":[406,8],\"Type\":\"dtis\"},{\"Mentions\":[[124,2]],\"Referant\":[449,2],\"Type\":\"dtis\"},{\"Mentions\":[[124,2]],\"Referant\":[546,2],\"Type\":\"dtis\"},{\"Mentions\":[[136,7]],\"Referant\":[587,8],\"Type\":\"dtis\"},{\"Mentions\":[[136,7]],\"Referant\":[629,8],\"Type\":\"dtis\"},{\"Mentions\":[[136,7]],\"Referant\":[677,8],\"Type\":\"dtis\"},{\"Mentions\":[[124,2]],\"Referant\":[753,2],\"Type\":\"dtis\"},{\"Mentions\":[[279,18]],\"Referant\":[766,15],\"Type\":\"dbis\"},{\"Mentions\":[[136,7]],\"Referant\":[861,8],\"Type\":\"dtis\"},{\"Mentions\":[[136,7]],\"Referant\":[946,8],\"Type\":\"dtis\"},{\"Mentions\":[[136,7]],\"Referant\":[1038,8],\"Type\":\"dtis\"},{\"Mentions\":[[136,7]],\"Referant\":[1120,8],\"Type\":\"dtis\"},{\"Mentions\":[[279,18]],\"Referant\":[1166,15],\"Type\":\"dbis\"},{\"Mentions\":[[136,7]],\"Referant\":[1276,8],\"Type\":\"dtis\"},{\"Mentions\":[[136,7]],\"Referant\":[1303,8],\"Type\":\"dtis\"},{\"Mentions\":[[124,2]],\"Referant\":[1398,2],\"Type\":\"dtis\"},{\"Mentions\":[[136,7]],\"Referant\":[1486,7],\"Type\":\"dtis\"},{\"Mentions\":[[136,7]],\"Referant\":[1518,8],\"Type\":\"dtis\"},{\"Mentions\":[[136,7]],\"Referant\":[1573,8],\"Type\":\"dtis\"},{\"Mentions\":[[136,7]],\"Referant\":[1599,8],\"Type\":\"dtis\"},{\"Mentions\":[[136,7]],\"Referant\":[1715,8],\"Type\":\"dtis\"},{\"Mentions\":[[124,2]],\"Referant\":[1793,2],\"Type\":\"dtis\"},{\"Mentions\":[[23,7]],\"Referant\":[1937,7],\"Type\":\"dtis\"},{\"Mentions\":[[34,7]],\"Referant\":[1946,7],\"Type\":\"dtis\"},{\"Mentions\":[[34,7]],\"Referant\":[1994,8],\"Type\":\"dtis\"},{\"Mentions\":[[34,7]],\"Referant\":[2229,7],\"Type\":\"dtis\"},{\"Mentions\":[[23,7]],\"Referant\":[2240,7],\"Type\":\"dtis\"},{\"Mentions\":[[1373,10]],\"Referant\":[1496,2],\"Type\":\"ppas\"},{\"Mentions\":[[385,8]],\"Referant\":[415,6],\"Type\":\"gsis\"},{\"Mentions\":[[279,18]],\"Referant\":[524,7],\"Type\":\"gfas\"},{\"Mentions\":[[607,16]],\"Referant\":[686,11],\"Type\":\"gfas\"},{\"Mentions\":[[202,21]],\"Referant\":[607,16],\"Type\":\"dbis\"},{\"Mentions\":[[415,6]],\"Referant\":[870,8],\"Type\":\"gsis\"},{\"Mentions\":[[870,8]],\"Referant\":[1129,11],\"Type\":\"gmis\"},{\"Mentions\":[[766,15]],\"Referant\":[1154,10],\"Type\":\"gfas\"},{\"Mentions\":[[1129,11]],\"Referant\":[1582,7],\"Type\":\"gmas\"},{\"Mentions\":[[1166,15]],\"Referant\":[1373,10],\"Type\":\"gfas\"},{\"Mentions\":[],\"Referant\":[1373,10],\"Type\":\"ghps\"},{\"Mentions\":[[385,8]],\"Referant\":[1724,9],\"Type\":\"gtis\"},{\"Mentions\":[[385,8]],\"Referant\":[1312,8],\"Type\":\"gtis\"},{\"Mentions\":[[1486,7]],\"Referant\":[1776,6],\"Type\":\"gfps\"},{\"Mentions\":[[1957,12],[1946,7],[1937,7]],\"Referant\":[1876,29],\"Type\":\"gfpg\"}]}",
            "tags":[
            ]
        },
        {
            "id":1365734,
            "type":"manualCoreferences",
            "version":2,
            "dateCreated":"2019-03-07T12:58:00.861+02:00",
            "dateModified":"2019-03-07T12:58:00.861+02:00",
            "content":"{\"coreferences\":[{\"Mentions\":[[279,18]],\"Referant\":[401,3],\"Type\":\"pras\"},{\"Mentions\":[[1331,5]],\"Referant\":[1338,5],\"Type\":\"peas\"},{\"Mentions\":[[1166,15]],\"Referant\":[1369,2],\"Type\":\"pras\"},{\"Mentions\":[[1373,10]],\"Referant\":[1426,2],\"Type\":\"pras\"},{\"Mentions\":[[1533,14]],\"Referant\":[1549,4],\"Type\":\"peas\"},{\"Mentions\":[[2154,5]],\"Referant\":[2161,6],\"Type\":\"peas\"},{\"Mentions\":[[136,7]],\"Referant\":[185,8],\"Type\":\"dtis\"},{\"Mentions\":[[107,15]],\"Referant\":[322,2],\"Type\":\"dbis\"},{\"Mentions\":[[136,7]],\"Referant\":[376,8],\"Type\":\"dtis\"},{\"Mentions\":[[136,7]],\"Referant\":[406,8],\"Type\":\"dtis\"},{\"Mentions\":[[107,15]],\"Referant\":[449,2],\"Type\":\"dtis\"},{\"Mentions\":[[107,15]],\"Referant\":[546,2],\"Type\":\"dtis\"},{\"Mentions\":[[136,7]],\"Referant\":[587,8],\"Type\":\"dtis\"},{\"Mentions\":[[136,7]],\"Referant\":[629,8],\"Type\":\"dtis\"},{\"Mentions\":[[136,7]],\"Referant\":[677,8],\"Type\":\"dtis\"},{\"Mentions\":[[124,2]],\"Referant\":[753,2],\"Type\":\"dtis\"},{\"Mentions\":[[279,18]],\"Referant\":[766,15],\"Type\":\"dais\"},{\"Mentions\":[[136,7]],\"Referant\":[861,8],\"Type\":\"dtis\"},{\"Mentions\":[[136,7]],\"Referant\":[946,8],\"Type\":\"dtis\"},{\"Mentions\":[[136,7]],\"Referant\":[1038,8],\"Type\":\"dtis\"},{\"Mentions\":[[136,7]],\"Referant\":[1120,8],\"Type\":\"dtis\"},{\"Mentions\":[[279,18]],\"Referant\":[1166,15],\"Type\":\"dais\"},{\"Mentions\":[[136,7]],\"Referant\":[1276,8],\"Type\":\"dtis\"},{\"Mentions\":[[136,7]],\"Referant\":[1303,8],\"Type\":\"dtis\"},{\"Mentions\":[[107,15]],\"Referant\":[1398,2],\"Type\":\"dtis\"},{\"Mentions\":[[136,7]],\"Referant\":[1486,7],\"Type\":\"dtis\"},{\"Mentions\":[[136,7]],\"Referant\":[1518,8],\"Type\":\"dtis\"},{\"Mentions\":[[136,7]],\"Referant\":[1573,8],\"Type\":\"dtis\"},{\"Mentions\":[[136,7]],\"Referant\":[1599,8],\"Type\":\"dtis\"},{\"Mentions\":[[136,7]],\"Referant\":[1715,8],\"Type\":\"dtis\"},{\"Mentions\":[[124,2]],\"Referant\":[1793,2],\"Type\":\"dtis\"},{\"Mentions\":[[23,7]],\"Referant\":[1937,7],\"Type\":\"dtis\"},{\"Mentions\":[[34,7]],\"Referant\":[1946,7],\"Type\":\"dtis\"},{\"Mentions\":[[34,7]],\"Referant\":[1994,8],\"Type\":\"dtis\"},{\"Mentions\":[[34,7]],\"Referant\":[2229,7],\"Type\":\"dtis\"},{\"Mentions\":[[23,7]],\"Referant\":[2240,7],\"Type\":\"dtis\"},{\"Mentions\":[[1373,10]],\"Referant\":[1496,2],\"Type\":\"pras\"},{\"Mentions\":[[385,8]],\"Referant\":[415,6],\"Type\":\"gsis\"},{\"Mentions\":[[279,18]],\"Referant\":[524,7],\"Type\":\"gfas\"},{\"Mentions\":[[607,16]],\"Referant\":[686,11],\"Type\":\"gfas\"},{\"Mentions\":[[202,21]],\"Referant\":[607,16],\"Type\":\"dbis\"},{\"Mentions\":[[766,15]],\"Referant\":[789,11],\"Type\":\"gfas\"},{\"Mentions\":[[415,6]],\"Referant\":[870,8],\"Type\":\"gsis\"},{\"Mentions\":[[870,8]],\"Referant\":[1129,11],\"Type\":\"gmis\"},{\"Mentions\":[[766,15]],\"Referant\":[1154,10],\"Type\":\"gfas\"},{\"Mentions\":[[1129,11]],\"Referant\":[1582,7],\"Type\":\"gmas\"},{\"Mentions\":[[1166,15]],\"Referant\":[1373,10],\"Type\":\"gfas\"},{\"Mentions\":[],\"Referant\":[1373,10],\"Type\":\"ghps\"},{\"Mentions\":[[164,19]],\"Referant\":[452,21],\"Type\":\"dtis\"},{\"Mentions\":[[1373,10]],\"Referant\":[2301,6],\"Type\":\"gfas\"},{\"Mentions\":[[164,19]],\"Referant\":[1220,21],\"Type\":\"dtis\"},{\"Mentions\":[[385,8]],\"Referant\":[1312,8],\"Type\":\"gtis\"},{\"Mentions\":[[385,8]],\"Referant\":[1724,9],\"Type\":\"gtis\"},{\"Mentions\":[[107,15]],\"Referant\":[124,2],\"Type\":\"dbis\"}]}",
            "tags":[
            ]
        }
    ]
}