{
    "id":116404,
    "corpusName":"Žiniasklaidos tekstai",
    "corpusId":109,
    "name":"1076_tekstas.txt",
    "comment":"2016 m. lapkričio 14 d. 16:20",
    "dateCreated":"2018-12-07T12:49:03.343+02:00",
    "dateModified":"2019-11-21T11:45:45.712+02:00",
    "content":"Borisas Johnsonas: D. Trumpas yra gera proga Europai\nIšrinktasis JAV prezidentas Donaldas Trumpas yra žmogus, su kuriuo Didžioji Britanija ir Europos Sąjunga gali sudarinėti sandorius, pirmadienį pareiškė Didžiosios Britanijos užsienio reikalų ministras Borisas Johnsonas.\n„Donaldas Trumpas, kaip jau sakiau anksčiau, yra sandorių sudarinėtojas, todėl manau, kad tai gali būti gerai Britanijai, taip pat gerai ir Europai“, – pareiškė B. Johnsonas, atvykęs į ES užsienio reikalų ministrų susitikimą, praleidęs sekmadienio vakarą vykusią ministrų vakarienę.\n„Manau, kad mums visiems reikia palaukti ir pamatysime, ką jie sugalvos, bet aš galvoju, kad mes turėtumėme tai vertinti kaip pasitaikiusią progą“, – pridūrė jis.\nNetikėta D. Trumpo pergalė JAV prezidento rinkimuose sukėlė didžiulį nerimą Europoje po jo rinkiminės kampanijos pareiškimų, kad jis gali nutraukti Vašingtono įsipareigojimus NATO.\nES užsienio politikos vadovė Federica Mogherini sekmadienio vakarą surengė neoficialią vakarienę, kurios metu ministrai turėjo apsikeisti nuomonėmis dėl JAV ir ES santykių plėtros po rinkimų JAV. Tačiau B. Johnsonas šioje vakarienėje dalyvauti atsisakė, pareiškęs, kad tai bus blogas ženklas naujai išrinktam JAV prezidentui.\nPo sekmadienio susitikimo F. Mogherini sakė, kad ji tikisi „labai tvirtos partnerystės“ su D.Trumpo administracija, tačiau perspėjo, jog ES negali tiesiog laukti, kad pamatytų, ką jis pasiūlys.\n„Šiuo metu mes negalime sau leisti susitaikyti su „palauk ir pamatysi“ požiūriu, nes pasaulis nestovi vietoje, Europa nestovi vietoje, krizė nestovi vietoje, kaip ir galimybės, kuriomis mes galime pasinaudoti“, – sakė ji.\nF. Mogherini yra parengusi Globalią strategiją, kuri turėtų užtikrinti ES bendros gynybos politiką, bet Britanija ir kelios kitos ES narės priešinasi jos planams, nes mano, kad jie dubliuojasi JAV vadovaujamo Šiaurės Aljanso, kuris užtikrino Europos saugumą nuo 1949 metų, strategija.\nB. Johnsonas žurnalistams sakė, kad glaudesnis ES bendradarbiavimas gynybos srityje ir išlaidų gynybai didinimas yra teigiami dalykai, tačiau tai neturėtų būti daroma NATO sąskaita.\n„Kuriant šias ES struktūras, svarbu (žiūrėti), kad jos papildytų NATO, – kalbėjo B. Johnsonas. – Nereikėtų pakenkti esminei saugumo struktūrai, kuri mumis rūpinosi pastaruosius 70 metų“.",
    "source":"Delfi.lt",
    "url":"http://archive.ph/i7ZuU",
    "lexemeCount":383,
    "tags":[
    ],
    "annotationLayers":[
        {
            "id":1373735,
            "type":"anaphora_resolution",
            "version":3,
            "dateCreated":"2019-11-21T18:19:42.703+02:00",
            "dateModified":"2019-11-21T18:19:42.705+02:00",
            "content":"{\"anaphora_resolution\":[{\"ref\":[254,17],\"anaphor\":[[714,3]]}]}",
            "tags":[
            ]
        },
        {
            "id":1373732,
            "type":"lex",
            "version":1,
            "dateCreated":"2019-11-21T18:19:41.301+02:00",
            "dateModified":"2019-11-21T18:19:41.303+02:00",
            "content":"{\"seg\":[[0,7],[8,9],[17,1],[19,2],[22,7],[30,3],[34,4],[39,5],[45,7],[53,11],[65,3],[69,11],[81,8],[90,7],[98,3],[102,6],[108,1],[110,2],[113,6],[120,8],[129,9],[139,2],[142,7],[150,7],[158,4],[163,10],[174,9],[183,1],[185,10],[196,8],[205,10],[216,10],[227,8],[236,7],[244,9],[254,7],[262,9],[271,1],[273,1],[274,8],[283,7],[290,1],[292,4],[297,3],[301,6],[308,8],[316,1],[318,3],[322,8],[331,13],[344,1],[346,5],[352,5],[357,1],[359,3],[363,3],[367,4],[372,4],[377,5],[383,10],[393,1],[395,8],[404,5],[410,2],[413,7],[420,1],[421,1],[423,1],[425,8],[434,2],[437,9],[446,1],[448,7],[456,1],[458,2],[461,8],[470,7],[478,8],[487,10],[497,1],[499,9],[509,11],[521,6],[528,7],[536,8],[545,9],[554,1],[556,1],[557,5],[562,1],[564,3],[568,4],[573,7],[581,6],[588,8],[597,2],[600,10],[610,1],[612,2],[615,3],[619,8],[627,1],[629,3],[633,2],[636,7],[643,1],[645,3],[649,3],[653,10],[664,3],[668,8],[677,4],[682,13],[696,5],[701,1],[702,1],[704,1],[706,7],[714,3],[717,1],[719,8],[728,2],[731,6],[738,7],[746,3],[750,10],[761,10],[772,6],[779,8],[788,6],[795,8],[804,2],[807,2],[810,10],[821,10],[832,10],[842,1],[844,3],[848,3],[852,4],[857,9],[867,10],[878,15],[894,4],[898,1],[900,2],[903,8],[912,9],[922,6],[929,8],[938,9],[948,11],[960,6],[967,7],[975,11],[987,9],[996,1],[998,6],[1005,4],[1010,9],[1020,6],[1027,10],[1038,10],[1049,3],[1053,3],[1057,2],[1060,2],[1063,8],[1072,7],[1080,2],[1083,7],[1091,3],[1094,1],[1096,6],[1103,2],[1106,9],[1116,5],[1122,11],[1134,9],[1144,8],[1152,1],[1154,9],[1163,1],[1165,3],[1169,3],[1173,3],[1177,6],[1184,7],[1192,6],[1199,9],[1209,3],[1213,11],[1224,1],[1226,2],[1229,11],[1241,10],[1252,2],[1255,9],[1265,4],[1269,1],[1271,3],[1275,2],[1278,6],[1285,1],[1286,5],[1292,7],[1300,12],[1312,1],[1314,2],[1317,1],[1318,1],[1319,6],[1326,14],[1340,1],[1342,6],[1349,8],[1357,1],[1359,3],[1363,2],[1366,6],[1373,7],[1381,6],[1387,1],[1389,3],[1393,8],[1401,1],[1403,2],[1406,3],[1410,8],[1418,1],[1420,1],[1421,4],[1426,4],[1431,3],[1435,8],[1444,3],[1448,6],[1455,11],[1467,2],[1470,1],[1471,6],[1478,2],[1481,8],[1489,1],[1491,8],[1499,1],[1501,3],[1505,8],[1514,7],[1522,7],[1529,1],[1531,6],[1538,7],[1546,7],[1553,1],[1555,5],[1561,7],[1569,7],[1576,1],[1578,4],[1583,2],[1586,9],[1595,1],[1597,8],[1606,3],[1610,6],[1617,11],[1628,1],[1629,1],[1631,1],[1633,4],[1638,2],[1640,1],[1642,2],[1645,9],[1655,3],[1659,9],[1669,8],[1678,10],[1688,1],[1690,4],[1695,6],[1702,10],[1713,2],[1716,7],[1724,7],[1732,8],[1740,1],[1742,3],[1746,9],[1756,2],[1759,6],[1766,5],[1772,2],[1775,5],[1781,10],[1792,3],[1796,7],[1803,1],[1805,3],[1809,4],[1813,1],[1815,3],[1819,3],[1823,11],[1835,3],[1839,11],[1851,7],[1859,7],[1866,1],[1868,5],[1874,9],[1884,7],[1892,7],[1900,3],[1904,4],[1909,4],[1913,1],[1915,10],[1925,1],[1927,2],[1930,9],[1940,12],[1953,4],[1957,1],[1959,3],[1963,10],[1974,2],[1977,17],[1995,7],[2003,7],[2011,2],[2014,7],[2022,7],[2030,9],[2040,3],[2044,8],[2053,7],[2060,1],[2062,6],[2069,3],[2073,8],[2082,4],[2087,6],[2094,4],[2099,8],[2107,1],[2109,1],[2110,7],[2118,4],[2123,2],[2126,10],[2136,1],[2138,6],[2145,1],[2146,7],[2153,1],[2154,1],[2156,3],[2160,3],[2164,9],[2174,4],[2178,1],[2180,1],[2182,7],[2190,2],[2193,9],[2202,1],[2204,1],[2206,9],[2216,8],[2225,7],[2233,7],[2241,10],[2251,1],[2253,4],[2258,5],[2264,8],[2273,12],[2286,2],[2289,4],[2293,1],[2294,1]],\"s\":[[0,52],[53,219],[273,282],[556,162],[719,180],[900,195],[1096,129],[1226,93],[1319,100],[1420,221],[1642,284],[1927,181],[2109,94],[2204,91]],\"p\":[[0,52],[53,219],[273,282],[556,162],[719,180],[900,325],[1226,193],[1420,221],[1642,284],[1927,181],[2109,186]]}",
            "tags":[
            ]
        },
        {
            "id":1365689,
            "type":"manualCoreferences",
            "version":1,
            "dateCreated":"2019-03-05T19:45:03.930+02:00",
            "dateModified":"2019-03-05T19:45:03.930+02:00",
            "content":"{\"coreferences\":[{\"Mentions\":[[434,12]],\"Referant\":[714,3],\"Type\":\"ppas\"},{\"Mentions\":[[728,9]],\"Referant\":[807,2],\"Type\":\"ppps\"},{\"Mentions\":[[728,9]],\"Referant\":[848,3],\"Type\":\"ppps\"},{\"Mentions\":[[987,9]],\"Referant\":[998,6],\"Type\":\"peas\"},{\"Mentions\":[[1252,12]],\"Referant\":[1638,2],\"Type\":\"ppas\"},{\"Mentions\":[[1678,10]],\"Referant\":[1690,4],\"Type\":\"peas\"},{\"Mentions\":[[1642,12]],\"Referant\":[1792,3],\"Type\":\"ppas\"},{\"Mentions\":[[1851,15]],\"Referant\":[1868,5],\"Type\":\"peas\"},{\"Mentions\":[[2123,13]],\"Referant\":[2160,3],\"Type\":\"ppas\"},{\"Mentions\":[[2241,10]],\"Referant\":[2253,4],\"Type\":\"peas\"},{\"Mentions\":[[274,16]],\"Referant\":[728,9],\"Type\":\"dbis\"},{\"Mentions\":[[413,7]],\"Referant\":[795,8],\"Type\":\"dtis\"},{\"Mentions\":[[1053,3]],\"Referant\":[1091,3],\"Type\":\"dtis\"},{\"Mentions\":[[434,12]],\"Referant\":[1103,12],\"Type\":\"dtis\"},{\"Mentions\":[[929,18]],\"Referant\":[1252,12],\"Type\":\"dbis\"},{\"Mentions\":[[274,16]],\"Referant\":[1317,8],\"Type\":\"dbis\"},{\"Mentions\":[[1060,2]],\"Referant\":[1363,2],\"Type\":\"dtis\"},{\"Mentions\":[[413,7]],\"Referant\":[1531,6],\"Type\":\"dtis\"},{\"Mentions\":[[929,18]],\"Referant\":[1642,12],\"Type\":\"dbis\"},{\"Mentions\":[[1060,2]],\"Referant\":[1713,2],\"Type\":\"dtis\"},{\"Mentions\":[[383,10]],\"Referant\":[1746,9],\"Type\":\"dtis\"},{\"Mentions\":[[746,3]],\"Referant\":[1835,3],\"Type\":\"dtis\"},{\"Mentions\":[[413,7]],\"Referant\":[1884,7],\"Type\":\"dtis\"},{\"Mentions\":[[434,12]],\"Referant\":[1927,12],\"Type\":\"dtis\"},{\"Mentions\":[[1060,2]],\"Referant\":[1974,2],\"Type\":\"dtis\"},{\"Mentions\":[[894,4]],\"Referant\":[2094,4],\"Type\":\"dtis\"},{\"Mentions\":[[894,4]],\"Referant\":[2174,4],\"Type\":\"dtis\"},{\"Mentions\":[[434,12]],\"Referant\":[2190,12],\"Type\":\"dtis\"},{\"Mentions\":[[728,9]],\"Referant\":[1213,11],\"Type\":\"gfas\"},{\"Mentions\":[[1252,12]],\"Referant\":[1275,2],\"Type\":\"ppas\"},{\"Mentions\":[[1317,8]],\"Referant\":[1406,3],\"Type\":\"ppas\"},{\"Mentions\":[[1586,9]],\"Referant\":[1597,8],\"Type\":\"peas\"},{\"Mentions\":[[1796,7]],\"Referant\":[1819,3],\"Type\":\"ppas\"},{\"Mentions\":[[434,12]],\"Referant\":[633,2],\"Type\":\"ppas\"},{\"Mentions\":[[1053,3]],\"Referant\":[867,10],\"Type\":\"dmis\"},{\"Mentions\":[[894,4]],\"Referant\":[1851,15],\"Type\":\"dsis\"},{\"Mentions\":[[274,70]],\"Referant\":[346,5],\"Type\":\"a-as\"},{\"Mentions\":[[536,18]],\"Referant\":[1122,11],\"Type\":\"gais\"},{\"Mentions\":[[81,16]],\"Referant\":[274,16],\"Type\":\"dtis\"},{\"Mentions\":[[0,17]],\"Referant\":[254,17],\"Type\":\"dtis\"},{\"Mentions\":[[81,16]],\"Referant\":[19,10],\"Type\":\"dbis\"},{\"Mentions\":[[254,17]],\"Referant\":[434,12],\"Type\":\"dbis\"},{\"Mentions\":[[142,15]],\"Referant\":[1060,2],\"Type\":\"dbis\"},{\"Mentions\":[[45,7]],\"Referant\":[413,7],\"Type\":\"dtis\"},{\"Mentions\":[[45,7]],\"Referant\":[142,15],\"Type\":\"dmis\"},{\"Mentions\":[[205,21]],\"Referant\":[383,10],\"Type\":\"dais\"},{\"Mentions\":[[120,18]],\"Referant\":[205,21],\"Type\":\"dtis\"},{\"Mentions\":[[65,3]],\"Referant\":[1053,3],\"Type\":\"dtis\"},{\"Mentions\":[[65,3]],\"Referant\":[746,3],\"Type\":\"dtis\"}]}",
            "tags":[
            ]
        },
        {
            "id":1374065,
            "type":"manualCoreferences",
            "version":2,
            "dateCreated":"2020-01-16T12:45:45.053+02:00",
            "dateModified":"2020-01-16T12:45:45.053+02:00",
            "content":"{\"coreferences\":[{\"Mentions\":[[434,12]],\"Referant\":[714,3],\"Type\":\"ppas\"},{\"Mentions\":[[728,9]],\"Referant\":[807,2],\"Type\":\"ppps\"},{\"Mentions\":[[728,9]],\"Referant\":[848,3],\"Type\":\"ppps\"},{\"Mentions\":[[987,9]],\"Referant\":[998,6],\"Type\":\"peas\"},{\"Mentions\":[[1252,12]],\"Referant\":[1638,2],\"Type\":\"ppas\"},{\"Mentions\":[[1678,10]],\"Referant\":[1690,4],\"Type\":\"peas\"},{\"Mentions\":[[1642,12]],\"Referant\":[1792,3],\"Type\":\"ppas\"},{\"Mentions\":[[1851,15]],\"Referant\":[1868,5],\"Type\":\"peas\"},{\"Mentions\":[[2241,10]],\"Referant\":[2253,4],\"Type\":\"peas\"},{\"Mentions\":[[274,16]],\"Referant\":[728,9],\"Type\":\"dbis\"},{\"Mentions\":[[413,7]],\"Referant\":[795,8],\"Type\":\"dtis\"},{\"Mentions\":[[1053,3]],\"Referant\":[1091,3],\"Type\":\"dtis\"},{\"Mentions\":[[434,12]],\"Referant\":[1103,12],\"Type\":\"dtis\"},{\"Mentions\":[[929,18]],\"Referant\":[1252,12],\"Type\":\"dbis\"},{\"Mentions\":[[274,16]],\"Referant\":[1317,8],\"Type\":\"dbis\"},{\"Mentions\":[[1060,2]],\"Referant\":[1363,2],\"Type\":\"dtis\"},{\"Mentions\":[[413,7]],\"Referant\":[1531,6],\"Type\":\"dtis\"},{\"Mentions\":[[929,18]],\"Referant\":[1642,12],\"Type\":\"dbis\"},{\"Mentions\":[[1060,2]],\"Referant\":[1713,2],\"Type\":\"dtis\"},{\"Mentions\":[[383,10]],\"Referant\":[1746,9],\"Type\":\"dtis\"},{\"Mentions\":[[746,3]],\"Referant\":[1835,3],\"Type\":\"dtis\"},{\"Mentions\":[[413,7]],\"Referant\":[1884,7],\"Type\":\"dtis\"},{\"Mentions\":[[434,12]],\"Referant\":[1927,12],\"Type\":\"dtis\"},{\"Mentions\":[[1060,2]],\"Referant\":[1974,2],\"Type\":\"dtis\"},{\"Mentions\":[[894,4]],\"Referant\":[2094,4],\"Type\":\"dtis\"},{\"Mentions\":[[894,4]],\"Referant\":[2174,4],\"Type\":\"dtis\"},{\"Mentions\":[[434,12]],\"Referant\":[2190,12],\"Type\":\"dtis\"},{\"Mentions\":[[728,9]],\"Referant\":[1213,11],\"Type\":\"gfas\"},{\"Mentions\":[[1252,12]],\"Referant\":[1275,2],\"Type\":\"ppas\"},{\"Mentions\":[[1317,8]],\"Referant\":[1406,3],\"Type\":\"ppas\"},{\"Mentions\":[[1586,9]],\"Referant\":[1597,8],\"Type\":\"peas\"},{\"Mentions\":[[434,12]],\"Referant\":[633,2],\"Type\":\"ppas\"},{\"Mentions\":[[1053,3]],\"Referant\":[867,10],\"Type\":\"dmis\"},{\"Mentions\":[[81,16]],\"Referant\":[274,16],\"Type\":\"dtis\"},{\"Mentions\":[[0,17]],\"Referant\":[254,17],\"Type\":\"dtis\"},{\"Mentions\":[[81,16]],\"Referant\":[19,10],\"Type\":\"dbis\"},{\"Mentions\":[[254,17]],\"Referant\":[434,12],\"Type\":\"dbis\"},{\"Mentions\":[[142,15]],\"Referant\":[1060,2],\"Type\":\"dbis\"},{\"Mentions\":[[45,7]],\"Referant\":[413,7],\"Type\":\"dtis\"},{\"Mentions\":[[45,7]],\"Referant\":[142,15],\"Type\":\"dmis\"},{\"Mentions\":[[205,21]],\"Referant\":[383,10],\"Type\":\"dais\"},{\"Mentions\":[[120,18]],\"Referant\":[205,21],\"Type\":\"dtis\"},{\"Mentions\":[[65,3]],\"Referant\":[1053,3],\"Type\":\"dtis\"},{\"Mentions\":[[65,3]],\"Referant\":[746,3],\"Type\":\"dtis\"}]}",
            "tags":[
            ]
        },
        {
            "id":1373733,
            "type":"morphology",
            "version":4,
            "dateCreated":"2019-11-21T18:19:41.673+02:00",
            "dateModified":"2019-11-21T18:19:41.678+02:00",
            "content":"{\"msd\":[[[\"Borisas\",\"Npmsnnf\"],[\"Borisas\",\"Npmsnns\"],[\"Borisa\",\"Npmpans\"]],[[\"Johnsonas\",\"X-\"]],[[\":\",\"Tn\"]],[[\"d.\",\"Ys\"],[\"D.\",\"Ys\"]],[[\"trumpas\",\"Agpmsnn\"],[\"trumpas\",\"Agpfpan\"],[\"Trumpa\",\"Npmpans\"],[\"trumpas\",\"Agpmsvn\"]],[[\"būti\",\"Vgmp3s--n--ni-\"],[\"būti\",\"Vgmp3p--n--ni-\"],[\"irti\",\"Vgmp3s--n--ni-\"],[\"būti\",\"Vgmp3---n--ni-\"],[\"irti\",\"Vgmp3p--n--ni-\"],[\"irti\",\"Vgmp3---n--ni-\"]],[[\"geras\",\"Agpfsnn\"],[\"geras\",\"Agpn--n\"],[\"geras\",\"Agpfsin\"],[\"geras\",\"Agpfsvn\"]],[[\"proga\",\"Ncfsnn-\"],[\"proga\",\"Ncfsin-\"],[\"proga\",\"Ncfsvn-\"]],[[\"Europa\",\"Npfsdng\"]],[[\"išrinkti\",\"Vgpa-smpnynn-p\"],[\"išrinktasis\",\"Ncmsnn-\"],[\"išrinkti\",\"Vgpa-smpnyvn-p\"]],[[\"JAV\",\"Ya\"]],[[\"prezidentas\",\"Ncmsnn-\"]],[[\"Donaldas\",\"Npmsnnf\"]],[[\"trumpas\",\"Agpmsnn\"],[\"trumpas\",\"Agpfpan\"],[\"Trumpa\",\"Npmpans\"],[\"trumpas\",\"Agpmsvn\"]],[[\"būti\",\"Vgmp3s--n--ni-\"],[\"būti\",\"Vgmp3p--n--ni-\"],[\"irti\",\"Vgmp3s--n--ni-\"],[\"būti\",\"Vgmp3---n--ni-\"],[\"irti\",\"Vgmp3p--n--ni-\"],[\"irti\",\"Vgmp3---n--ni-\"]],[[\"žmogus\",\"Ncmsnn-\"]],[[\",\",\"Tc\"]],[[\"su\",\"Sgi\"]],[[\"kuris\",\"Pgmsin\"]],[[\"didis\",\"Agpfsny\"],[\"didus\",\"Agpfsny\"],[\"didelis\",\"Agpfsny\"],[\"didus\",\"Agpfsvy\"],[\"didis\",\"Agpfsvy\"],[\"didelis\",\"Agpfsvy\"]],[[\"Britanija\",\"Npfsnng\"],[\"Britanija\",\"Npfsing\"],[\"Britanija\",\"Npfsvng\"]],[[\"ir\",\"Cg\"],[\"ir\",\"Qg\"]],[[\"Europa\",\"Npfsgng\"]],[[\"sąjunga\",\"Ncfsnn-\"],[\"sąjunga\",\"Ncfsin-\"],[\"sąjunga\",\"Ncfsvn-\"]],[[\"galėti\",\"Vgmp3s--n--ni-\"],[\"galėti\",\"Vgmp3p--n--ni-\"],[\"galėti\",\"Vgmp3---n--ni-\"],[\"galėti\",\"Vgmp2s--n--ni-\"],[\"galis\",\"Ncmsvn-\"]],[[\"sudarinėti\",\"Vgi-----n--n--\"],[\"sudarinėti\",\"Vgpa-pmpnnnn-p\"],[\"sudarinėti\",\"Vgpa-pmpnnvn-p\"]],[[\"sandoris\",\"Ncmpan-\"]],[[\",\",\"Tc\"]],[[\"pirmadienis\",\"Ncmsan-\"]],[[\"pareikšti\",\"Vgms3s--n--ni-\"],[\"pareikšti\",\"Vgms3p--n--ni-\"],[\"pareikšti\",\"Vgms3---n--ni-\"]],[[\"didis\",\"Agpfsgy\"],[\"didis\",\"Agpfpny\"],[\"didus\",\"Agpfsgy\"],[\"didelis\",\"Agpfsgy\"],[\"didus\",\"Agpfpny\"],[\"didelis\",\"Agpfpny\"],[\"didus\",\"Agpfpvy\"],[\"didis\",\"Agpfpvy\"],[\"didelis\",\"Agpfpvy\"]],[[\"Britanija\",\"Npfsgng\"]],[[\"užsienis\",\"Ncmsgn-\"]],[[\"reikalas\",\"Ncmpgn-\"]],[[\"ministras\",\"Ncmsnn-\"]],[[\"Borisas\",\"Npmsnnf\"],[\"Borisas\",\"Npmsnns\"],[\"Borisa\",\"Npmpans\"]],[[\"Johnsonas\",\"X-\"]],[[\".\",\"Tp\"]],[[\"„\",\"Tu\"]],[[\"Donaldas\",\"Npmsnnf\"]],[[\"trumpas\",\"Agpmsnn\"],[\"trumpas\",\"Agpfpan\"],[\"Trumpa\",\"Npmpans\"],[\"trumpas\",\"Agpmsvn\"]],[[\",\",\"Tc\"]],[[\"kaip\",\"Cg\"],[\"kaip\",\"Rgp\"],[\"kaip\",\"Qg\"]],[[\"jau\",\"Rgp\"],[\"jau\",\"Qg\"]],[[\"sakyti\",\"Vgms1s--n--ni-\"]],[[\"anksti\",\"Rgc\"],[\"ankstus\",\"Agcn--n\"]],[[\",\",\"Tc\"]],[[\"būti\",\"Vgmp3s--n--ni-\"],[\"būti\",\"Vgmp3p--n--ni-\"],[\"irti\",\"Vgmp3s--n--ni-\"],[\"būti\",\"Vgmp3---n--ni-\"],[\"irti\",\"Vgmp3p--n--ni-\"],[\"irti\",\"Vgmp3---n--ni-\"]],[[\"sandoris\",\"Ncmpgn-\"]],[[\"sudarinėtojas\",\"Ncmsnn-\"],[\"sudarinėtoja\",\"Ncfpan-\"]],[[\",\",\"Tc\"]],[[\"todėl\",\"Rgp\"]],[[\"manyti\",\"Vgmp1s--n--ni-\"]],[[\",\",\"Tc\"]],[[\"kad\",\"Cg\"],[\"kad\",\"Qg\"]],[[\"tai\",\"Qg\"],[\"tai\",\"Cg\"],[\"tas\",\"Pgfsdn\"],[\"tai\",\"Pg---n\"],[\"tas\",\"Pgnsnn\"]],[[\"galėti\",\"Vgmp3s--n--ni-\"],[\"galėti\",\"Vgmp3p--n--ni-\"],[\"galėti\",\"Vgmp3---n--ni-\"],[\"galėti\",\"Vgmp2s--n--ni-\"],[\"galis\",\"Ncmsvn-\"]],[[\"būti\",\"Vgi-----n--n--\"],[\"būti\",\"Vgpa-pmpnnnn-p\"],[\"būti\",\"Vgpa-pmpnnvn-p\"]],[[\"gerai\",\"Rgp\"],[\"geras\",\"Agpfsdn\"]],[[\"Britanija\",\"Npfsdng\"]],[[\",\",\"Tc\"]],[[\"taip pat\",\"Rgp\"]],[[\"gerai\",\"Rgp\"],[\"geras\",\"Agpfsdn\"]],[[\"ir\",\"Cg\"],[\"ir\",\"Qg\"]],[[\"Europa\",\"Npfsdng\"]],[[\"“\",\"Tu\"]],[[\",\",\"Tc\"]],[[\"–\",\"Th\"]],[[\"pareikšti\",\"Vgms3s--n--ni-\"],[\"pareikšti\",\"Vgms3p--n--ni-\"],[\"pareikšti\",\"Vgms3---n--ni-\"]],[[\"B.\",\"Ys\"]],[[\"Johnsonas\",\"X-\"]],[[\",\",\"Tc\"]],[[\"atvykti\",\"Vgps-smannnn-p\"],[\"atvykti\",\"Vgps-smannvn-p\"]],[[\"į\",\"Sga\"]],[[\"ES\",\"Ya\"]],[[\"užsienis\",\"Ncmsgn-\"]],[[\"reikalas\",\"Ncmpgn-\"]],[[\"ministras\",\"Ncmpgn-\"]],[[\"susitikimas\",\"Ncmsan-\"]],[[\",\",\"Tc\"]],[[\"praleisti\",\"Vgps-smannnn-p\"],[\"praleisti\",\"Vgps-smannvn-p\"]],[[\"sekmadienis\",\"Ncmsgn-\"]],[[\"vakaras\",\"Ncmsan-\"]],[[\"vykti\",\"Vgps-sfannan-p\"],[\"vykęs\",\"Agpfsan\"]],[[\"ministras\",\"Ncmpgn-\"]],[[\"vakarienė\",\"Ncfsan-\"]],[[\".\",\"Tp\"]],[[\"„\",\"Tu\"]],[[\"manyti\",\"Vgmp1s--n--ni-\"]],[[\",\",\"Tc\"]],[[\"kad\",\"Cg\"],[\"kad\",\"Qg\"]],[[\"aš\",\"Pg-pdn\"]],[[\"visas\",\"Pgmpdn\"]],[[\"reikėti\",\"Vgmp3p--n--ni-\"],[\"reikėti\",\"Vgmp3s--n--ni-\"],[\"reikti\",\"Vgmp3s--n--ni-\"],[\"reikėti\",\"Vgmp3p--n--ni-\"],[\"reikti\",\"Vgmp3p--n--ni-\"],[\"reikti\",\"Vgmp3---n--ni-\"]],[[\"palaukti\",\"Vgi-----n--n--\"],[\"palaukti\",\"Vgpa-pmpnnnn-p\"],[\"palaukti\",\"Vgpa-pmpnnvn-p\"]],[[\"ir\",\"Cg\"],[\"ir\",\"Qg\"]],[[\"pamatyti\",\"Vgmf1p--n--ni-\"]],[[\",\",\"Tc\"]],[[\"kas\",\"Pg--an\"]],[[\"jis\",\"Pgmpnn\"]],[[\"sugalvoti\",\"Vgmf3p--n--ni-\"],[\"sugalvoti\",\"Vgmf3s--n--ni-\"],[\"sugalvoti\",\"Vgmf3---n--ni-\"]],[[\",\",\"Tc\"]],[[\"bet\",\"Cg\"],[\"bet\",\"Qg\"]],[[\"aš\",\"Pg-snn\"]],[[\"galvoti\",\"Vgmp1s--n--ni-\"]],[[\",\",\"Tc\"]],[[\"kad\",\"Cg\"],[\"kad\",\"Qg\"]],[[\"aš\",\"Pg-pnn\"],[\"mesti\",\"Vgmf3s--n--ni-\"],[\"mesti\",\"Vgmf3p--n--ni-\"],[\"mesti\",\"Vgmf3---n--ni-\"]],[[\"turėti\",\"Vgm-1p--n--ns-\"]],[[\"tai\",\"Qg\"],[\"tai\",\"Cg\"],[\"tas\",\"Pgfsdn\"],[\"tai\",\"Pg---n\"],[\"tas\",\"Pgnsnn\"]],[[\"vertinti\",\"Vgi-----n--n--\"],[\"vertinti\",\"Vgpa-pmpnnnn-p\"],[\"vertinti\",\"Vgpa-pmpnnvn-p\"]],[[\"kaip\",\"Cg\"],[\"kaip\",\"Rgp\"],[\"kaip\",\"Qg\"]],[[\"pasitaikyti\",\"Vgps-sfannay-p\"]],[[\"proga\",\"Ncfsan-\"]],[[\"“\",\"Tu\"]],[[\",\",\"Tc\"]],[[\"–\",\"Th\"]],[[\"pridurti\",\"Vgms3p--n--ni-\"],[\"pridurti\",\"Vgms3p--n--ni-\"],[\"pridurti\",\"Vgms3---n--ni-\"]],[[\"jis\",\"Pgmsnn\"]],[[\".\",\"Tp\"]],[[\"netikėtas\",\"Agpfsnn\"],[\"netikėtas\",\"Agpn--n\"],[\"netikėti\",\"Vgpa-sfpynnn-p\"],[\"netikėtas\",\"Agpfsin\"],[\"netikėti\",\"Vgpa--npyn-n-p\"],[\"netikėti\",\"Vgpa-sfpynin-p\"],[\"netikėtas\",\"Agpfsvn\"],[\"netikėti\",\"Vgpa-sfpynvn-p\"]],[[\"d.\",\"Ys\"],[\"D.\",\"Ys\"]],[[\"trumpas\",\"Agpmsgn\"]],[[\"pergalė\",\"Ncfsnn-\"]],[[\"JAV\",\"Ya\"]],[[\"prezidentas\",\"Ncmsgn-\"]],[[\"rinkimai\",\"Ncmpln-\"]],[[\"sukelti\",\"Vgms3s--n--ni-\"],[\"sukelti\",\"Vgms3p--n--ni-\"],[\"sukelti\",\"Vgms3---n--ni-\"]],[[\"didžiulis\",\"Agpmsan\"]],[[\"nerimas\",\"Ncmsan-\"]],[[\"Europa\",\"Npfslng\"]],[[\"po\",\"Sgg\"],[\"po\",\"Sga\"],[\"po\",\"Sgi\"],[\"po\",\"Sgd\"]],[[\"jis\",\"Pgmsgn\"]],[[\"rinkiminis\",\"Agpfsgn\"],[\"rinkiminis\",\"Agpfpnn\"],[\"rinkiminis\",\"Agpfpvn\"]],[[\"kampanija\",\"Ncfsgn-\"],[\"kampanija\",\"Ncfpnn-\"],[\"kampanija\",\"Ncfpvn-\"]],[[\"pareiškimas\",\"Ncmpgn-\"]],[[\",\",\"Tc\"]],[[\"kad\",\"Cg\"],[\"kad\",\"Qg\"]],[[\"jis\",\"Pgmsnn\"]],[[\"galėti\",\"Vgmp3s--n--ni-\"],[\"galėti\",\"Vgmp3p--n--ni-\"],[\"galėti\",\"Vgmp3---n--ni-\"],[\"galėti\",\"Vgmp2s--n--ni-\"],[\"galis\",\"Ncmsvn-\"]],[[\"nutraukti\",\"Vgi-----n--n--\"],[\"nutraukti\",\"Vgpa-pmpnnnn-p\"],[\"nutraukti\",\"Vgpa-pmpnnvn-p\"]],[[\"Vašingtonas\",\"Npmsgng\"]],[[\"įsipareigojimas\",\"Ncmpan-\"]],[[\"NATO\",\"Ya\"]],[[\".\",\"Tp\"]],[[\"ES\",\"Ya\"]],[[\"užsienis\",\"Ncmsgn-\"]],[[\"politika\",\"Ncfsgn-\"]],[[\"vadovė\",\"Ncfsnn-\"]],[[\"Federica\",\"X-\"]],[[\"Mogherini\",\"X-\"]],[[\"sekmadienis\",\"Ncmsgn-\"]],[[\"vakaras\",\"Ncmsan-\"]],[[\"surengti\",\"Vgms3s--n--ni-\"],[\"surengti\",\"Vgms3p--n--ni-\"],[\"surengti\",\"Vgms3---n--ni-\"]],[[\"neoficialus\",\"Agpfsan\"]],[[\"vakarienė\",\"Ncfsan-\"]],[[\",\",\"Tc\"]],[[\"kuris\",\"Pgfsgn\"],[\"kuris\",\"Pgfpnn\"]],[[\"metas\",\"Ncmsin-\"],[\"mesti\",\"Vgmp1s--n--ni-\"]],[[\"ministras\",\"Ncmpnn-\"],[\"ministras\",\"Ncmpvn-\"]],[[\"turėti\",\"Vgms3p--n--ni-\"],[\"turėti\",\"Vgms3s--n--ni-\"],[\"turėti\",\"Vgms3---n--ni-\"]],[[\"apsikeisti\",\"Vgi-----n--y--\"],[\"apsikeisti\",\"Vgpa-pmpnnny-p\"],[\"apsikeisti\",\"Vgpa-pmpnnvy-p\"]],[[\"nuomonė\",\"Ncfpin-\"]],[[\"dėl\",\"Sgg\"]],[[\"JAV\",\"Ya\"]],[[\"ir\",\"Cg\"],[\"ir\",\"Qg\"]],[[\"ES\",\"Ya\"]],[[\"santykis\",\"Ncmpgn-\"]],[[\"plėtra\",\"Ncfsgn-\"],[\"plėtra\",\"Ncfpnn-\"],[\"plėtra\",\"Ncfpvn-\"]],[[\"po\",\"Sgg\"],[\"po\",\"Sga\"],[\"po\",\"Sgi\"],[\"po\",\"Sgd\"]],[[\"rinkimai\",\"Ncmpgn-\"]],[[\"JAV\",\"Ya\"]],[[\".\",\"Tp\"]],[[\"tačiau\",\"Cg\"]],[[\"B.\",\"Ys\"]],[[\"Johnsonas\",\"X-\"]],[[\"šis\",\"Pgfsln\"]],[[\"vakarienė\",\"Ncfsln-\"]],[[\"dalyvauti\",\"Vgi-----n--n--\"],[\"dalyvauti\",\"Vgpa-pmpnnnn-p\"],[\"dalyvauti\",\"Vgpa-pmpnnvn-p\"]],[[\"atsisakyti\",\"Vgms3s--n--yi-\"],[\"atsisakyti\",\"Vgms3p--n--yi-\"],[\"atsisakyti\",\"Vgms3---n--yi-\"]],[[\",\",\"Tc\"]],[[\"pareikšti\",\"Vgps-smannnn-p\"],[\"pareikšti\",\"Vgps-smannvn-p\"]],[[\",\",\"Tc\"]],[[\"kad\",\"Cg\"],[\"kad\",\"Qg\"]],[[\"tai\",\"Cg\"],[\"tai\",\"Qg\"],[\"tas\",\"Pgfsdn\"],[\"tai\",\"Pg---n\"],[\"tas\",\"Pgnsnn\"]],[[\"būti\",\"Vgmf3s--n--ni-\"],[\"būti\",\"Vgmf3p--n--ni-\"],[\"būti\",\"Vgmf3---n--ni-\"],[\"busti\",\"Vgmf3s--n--ni-\"],[\"busti\",\"Vgmf3p--n--ni-\"],[\"busti\",\"Vgmf3---n--ni-\"]],[[\"blogas\",\"Agpmsnn\"],[\"blogas\",\"Agpfpan\"],[\"blogas\",\"Agpmsvn\"]],[[\"ženklas\",\"Ncmsnn-\"]],[[\"naujai\",\"Rgp\"],[\"naujas\",\"Agpfsdn\"]],[[\"išrinkti\",\"Vgpa-smpnndn-p\"],[\"išrinkti\",\"Vgpa-smpnnln-p\"]],[[\"JAV\",\"Ya\"]],[[\"prezidentas\",\"Ncmsdn-\"]],[[\".\",\"Tp\"]],[[\"po\",\"Sgg\"],[\"po\",\"Sga\"],[\"po\",\"Sgi\"],[\"po\",\"Sgd\"],[\"Po\",\"Npc--ng\"]],[[\"sekmadienis\",\"Ncmsgn-\"]],[[\"susitikimas\",\"Ncmsgn-\"]],[[\"F.\",\"Ys\"]],[[\"Mogherini\",\"X-\"]],[[\"sakė\",\"Ncfsnn-\"],[\"sakyti\",\"Vgms3s--n--ni-\"],[\"sakyti\",\"Vgms3p--n--ni-\"],[\"sakyti\",\"Vgms3---n--ni-\"]],[[\",\",\"Tc\"]],[[\"kad\",\"Cg\"],[\"kad\",\"Qg\"]],[[\"jis\",\"Pgfsnn\"]],[[\"tikėtis\",\"Vgmp3s--n--yi-\"],[\"tikėtis\",\"Vgmp3p--n--yi-\"],[\"tikėtis\",\"Vgmp3---n--yi-\"]],[[\"„\",\"Tu\"]],[[\"labai\",\"Rgp\"],[\"labas\",\"Agpfsdn\"]],[[\"tvirtas\",\"Agpfsgn\"],[\"tvirtas\",\"Agpfpnn\"],[\"tvirtas\",\"Agpfpvn\"]],[[\"partnerystė\",\"Ncfsgn-\"],[\"partnerystė\",\"Ncfpnn-\"],[\"partnerystė\",\"Ncfpvn-\"]],[[\"“\",\"Tu\"]],[[\"su\",\"Sgi\"]],[[\"D\",\"X-\"]],[[\".\",\"Tp\"]],[[\"trumpas\",\"Agpmsgn\"]],[[\"administracija\",\"Ncfsnn-\"],[\"administracija\",\"Ncfsin-\"],[\"administracija\",\"Ncfsvn-\"]],[[\",\",\"Tc\"]],[[\"tačiau\",\"Cg\"]],[[\"perspėti\",\"Vgms3s--n--ni-\"],[\"perspėti\",\"Vgms3p--n--ni-\"],[\"perspėti\",\"Vgms3---n--ni-\"]],[[\",\",\"Tc\"]],[[\"jog\",\"Cg\"]],[[\"ES\",\"Ya\"]],[[\"negalėti\",\"Vgmp3s--y--ni-\"],[\"negalėti\",\"Vgmp3p--y--ni-\"],[\"negalėti\",\"Vgmp2s--y--ni-\"],[\"negalėti\",\"Vgmp3---y--ni-\"]],[[\"tiesiog\",\"Rgp\"]],[[\"laukti\",\"Vgi-----n--n--\"],[\"laukti\",\"Vgpa-pmpnnnn-p\"],[\"laukti\",\"Vgpa-pmpnnvn-p\"]],[[\",\",\"Tc\"]],[[\"kad\",\"Cg\"],[\"kad\",\"Qg\"]],[[\"pamatyti\",\"Vgm-3s--n--ns-\"],[\"pamatyti\",\"Vgm-3p--n--ns-\"],[\"pamatyti\",\"Vgm-3---n--ns-\"],[\"pamatyti\",\"Vgpa-pmpnngn-p\"],[\"pamatyti\",\"Vgpa-pfpnngn-p\"]],[[\",\",\"Tc\"]],[[\"kas\",\"Pg--an\"]],[[\"jis\",\"Pgmsnn\"]],[[\"pasiūlyti\",\"Vgmf3s--n--ni-\"],[\"pasiūlyti\",\"Vgmf3p--n--ni-\"],[\"pasiūlyti\",\"Vgmf3---n--ni-\"]],[[\".\",\"Tp\"]],[[\"„\",\"Tu\"]],[[\"šis\",\"Pgmsin\"]],[[\"metas\",\"Ncmsin-\"],[\"mesti\",\"Vgmp1s--n--ni-\"]],[[\"aš\",\"Pg-pnn\"],[\"mesti\",\"Vgmf3s--n--ni-\"],[\"mesti\",\"Vgmf3p--n--ni-\"],[\"mesti\",\"Vgmf3---n--ni-\"]],[[\"negalėti\",\"Vgmp1p--y--ni-\"]],[[\"sau\",\"Rgp\"],[\"savęs\",\"Pg--dn\"],[\"sau\",\"Qg\"]],[[\"leisti\",\"Vgi-----n--n--\"],[\"leisti\",\"Vgpa-pmpnnnn-p\"],[\"leisti\",\"Vgpa-pmpnnvn-p\"]],[[\"susitaikyti\",\"Vgi-----n--y--\"],[\"susitaikyti\",\"Vgpa-pmpnnny-p\"],[\"susitaikyti\",\"Vgpa-pmpnnvy-p\"]],[[\"su\",\"Sgi\"]],[[\"„\",\"Tu\"]],[[\"palaukti\",\"Vgm-2s--n--nm-\"]],[[\"ir\",\"Cg\"],[\"ir\",\"Qg\"]],[[\"pamatyti\",\"Vgmf2s--n--ni-\"]],[[\"“\",\"Tu\"]],[[\"požiūris\",\"Ncmsin-\"]],[[\",\",\"Tc\"]],[[\"nes\",\"Cg\"]],[[\"pasaulis\",\"Ncmsnn-\"]],[[\"nestovėti\",\"Vgmp3s--y--ni-\"],[\"nestovėti\",\"Vgmp3p--y--ni-\"],[\"nestovėti\",\"Vgmp3---y--ni-\"],[\"nestovėti\",\"Vgmp2s--y--ni-\"]],[[\"vietoje\",\"Rgp\"],[\"vieta\",\"Ncfsln-\"],[\"vietoje\",\"Sgg\"]],[[\",\",\"Tc\"]],[[\"Europa\",\"Npfsnng\"],[\"Europa\",\"Npfsing\"],[\"Europa\",\"Npfsvng\"]],[[\"nestovėti\",\"Vgmp3s--y--ni-\"],[\"nestovėti\",\"Vgmp3p--y--ni-\"],[\"nestovėti\",\"Vgmp3---y--ni-\"],[\"nestovėti\",\"Vgmp2s--y--ni-\"]],[[\"vietoje\",\"Rgp\"],[\"vieta\",\"Ncfsln-\"],[\"vietoje\",\"Sgg\"]],[[\",\",\"Tc\"]],[[\"krizė\",\"Ncfsnn-\"]],[[\"nestovėti\",\"Vgmp3s--y--ni-\"],[\"nestovėti\",\"Vgmp3p--y--ni-\"],[\"nestovėti\",\"Vgmp3---y--ni-\"],[\"nestovėti\",\"Vgmp2s--y--ni-\"]],[[\"vietoje\",\"Rgp\"],[\"vieta\",\"Ncfsln-\"],[\"vietoje\",\"Sgg\"]],[[\",\",\"Tc\"]],[[\"kaip\",\"Cg\"],[\"kaip\",\"Rgp\"],[\"kaip\",\"Qg\"]],[[\"ir\",\"Qg\"],[\"ir\",\"Cg\"]],[[\"galimybė\",\"Ncfsgn-\"],[\"galimybė\",\"Ncfpnn-\"],[\"galimybė\",\"Ncfpvn-\"]],[[\",\",\"Tc\"]],[[\"kuris\",\"Pgfpin\"]],[[\"aš\",\"Pg-pnn\"],[\"mesti\",\"Vgmf3s--n--ni-\"],[\"mesti\",\"Vgmf3p--n--ni-\"],[\"mesti\",\"Vgmf3---n--ni-\"]],[[\"galėti\",\"Vgmp1p--n--ni-\"]],[[\"pasinaudoti\",\"Vgi-----n--y--\"],[\"pasinaudoti\",\"Vgpa-pmpnnny-p\"],[\"pasinaudoti\",\"Vgpa-pmpnnvy-p\"]],[[\"“\",\"Tu\"]],[[\",\",\"Tc\"]],[[\"–\",\"Th\"]],[[\"sakyti\",\"Vgms3p--n--ni-\"],[\"sakė\",\"Ncfsnn-\"],[\"sakyti\",\"Vgms3p--n--ni-\"],[\"sakyti\",\"Vgms3---n--ni-\"]],[[\"jis\",\"Pgfsnn\"]],[[\".\",\"Tp\"]],[[\"F.\",\"Ys\"]],[[\"Mogherini\",\"X-\"]],[[\"būti\",\"Vgmp3s--n--ni-\"],[\"būti\",\"Vgmp3p--n--ni-\"],[\"irti\",\"Vgmp3s--n--ni-\"],[\"būti\",\"Vgmp3---n--ni-\"],[\"irti\",\"Vgmp3p--n--ni-\"],[\"irti\",\"Vgmp3---n--ni-\"]],[[\"parengti\",\"Vgps-sfannnn-p\"],[\"parengti\",\"Vgps-sfannvn-p\"]],[[\"globalus\",\"Agpfsan\"]],[[\"strategija\",\"Ncfsan-\"]],[[\",\",\"Tc\"]],[[\"kuris\",\"Pgfsnn\"],[\"kurti\",\"Vgmp2s--n--ni-\"]],[[\"turėti\",\"Vgm-3s--n--ns-\"],[\"turėti\",\"Vgm-3p--n--ns-\"],[\"turėti\",\"Vgm-3---n--ns-\"],[\"turėti\",\"Vgpa-pmpnngn-p\"],[\"turėti\",\"Vgpa-pfpnngn-p\"]],[[\"užtikrinti\",\"Vgi-----n--n--\"],[\"užtikrinti\",\"Vgpa-pmpnnnn-p\"],[\"užtikrinti\",\"Vgpa-pmpnnvn-p\"]],[[\"ES\",\"Ya\"]],[[\"bendras\",\"Agpfsgn\"],[\"bendras\",\"Agpfpnn\"],[\"bendras\",\"Agpfpvn\"]],[[\"gynyba\",\"Ncfsgn-\"],[\"gynyba\",\"Ncfpnn-\"],[\"gynyba\",\"Ncfpvn-\"]],[[\"politika\",\"Ncfsan-\"],[\"politikas\",\"Ncmsan-\"]],[[\",\",\"Tc\"]],[[\"bet\",\"Cg\"],[\"bet\",\"Qg\"]],[[\"Britanija\",\"Npfsnng\"],[\"Britanija\",\"Npfsing\"],[\"Britanija\",\"Npfsvng\"]],[[\"ir\",\"Cg\"],[\"ir\",\"Qg\"]],[[\"keli\",\"Pgf-nn\"]],[[\"kitas\",\"Pgfpnn\"],[\"kitas\",\"Pgfsgn\"],[\"kitas\",\"Pgfpvn\"]],[[\"ES\",\"Ya\"]],[[\"narė\",\"Ncfpnn-\"],[\"narė\",\"Ncfsgn-\"],[\"narė\",\"Ncfpvn-\"]],[[\"priešintis\",\"Vgmp3p--n--yi-\"],[\"priešintis\",\"Vgmp3s--n--yi-\"],[\"priešintis\",\"Vgmp3---n--yi-\"]],[[\"jis\",\"Pgfsgn\"],[\"jis\",\"Pgfpnn\"],[\"joti\",\"Vgmf3s--n--ni-\"],[\"joti\",\"Vgmf3p--n--ni-\"],[\"joti\",\"Vgmf3---n--ni-\"]],[[\"planas\",\"Ncmpdn-\"]],[[\",\",\"Tc\"]],[[\"nes\",\"Cg\"]],[[\"aš\",\"Pg-sgn\"],[\"manyti\",\"Vgmp3s--n--ni-\"],[\"manyti\",\"Vgmp3p--n--ni-\"],[\"manas\",\"Pgmsgn\"],[\"manyti\",\"Vgmp3---n--ni-\"]],[[\",\",\"Tc\"]],[[\"kad\",\"Cg\"],[\"kad\",\"Qg\"]],[[\"jis\",\"Pgmpnn\"]],[[\"dubliuotis\",\"Vgmp3p--n--yi-\"],[\"dubliuotis\",\"Vgmp3s--n--yi-\"],[\"dubliuotis\",\"Vgmp3---n--yi-\"]],[[\"JAV\",\"Ya\"]],[[\"vadovauti\",\"Vgpp-smpnngn-p\"]],[[\"šiaurė\",\"Ncfsgn-\"]],[[\"aljansas\",\"Ncmsgn-\"]],[[\",\",\"Tc\"]],[[\"kuris\",\"Pgmsnn\"]],[[\"užtikrinti\",\"Vgms3s--n--ni-\"],[\"užtikrinti\",\"Vgms3p--n--ni-\"],[\"užtikrinti\",\"Vgms3---n--ni-\"]],[[\"Europa\",\"Npfsgng\"]],[[\"saugumas\",\"Ncmsan-\"]],[[\"nuo\",\"Sgg\"]],[[\"1949\",\"M----d-\"]],[[\"metai\",\"Ncmpgn-\"]],[[\",\",\"Tc\"]],[[\"strategija\",\"Ncfsnn-\"],[\"strategija\",\"Ncfsin-\"],[\"strategija\",\"Ncfsvn-\"]],[[\".\",\"Tp\"]],[[\"B.\",\"Ys\"]],[[\"Johnsonas\",\"X-\"]],[[\"žurnalistas\",\"Ncmpdn-\"]],[[\"sakyti\",\"Vgms3s--n--ni-\"],[\"sakė\",\"Ncfsnn-\"],[\"sakyti\",\"Vgms3p--n--ni-\"],[\"sakyti\",\"Vgms3---n--ni-\"]],[[\",\",\"Tc\"]],[[\"kad\",\"Cg\"],[\"kad\",\"Qg\"]],[[\"glaudus\",\"Agcmsnn\"],[\"glaudus\",\"Agcmsvn\"]],[[\"ES\",\"Ya\"]],[[\"bendradarbiavimas\",\"Ncmsnn-\"]],[[\"gynyba\",\"Ncfsgn-\"],[\"gynyba\",\"Ncfpnn-\"],[\"gynyba\",\"Ncfpvn-\"]],[[\"sritis\",\"Ncfsln-\"]],[[\"ir\",\"Cg\"],[\"ir\",\"Qg\"]],[[\"išlaidos\",\"Ncfpgn-\"],[\"išlaidus\",\"Agpmsan\"]],[[\"gynyba\",\"Ncfsdn-\"]],[[\"didinimas\",\"Ncmsnn-\"]],[[\"būti\",\"Vgmp3s--n--ni-\"],[\"būti\",\"Vgmp3p--n--ni-\"],[\"irti\",\"Vgmp3s--n--ni-\"],[\"būti\",\"Vgmp3---n--ni-\"],[\"irti\",\"Vgmp3p--n--ni-\"],[\"irti\",\"Vgmp3---n--ni-\"]],[[\"teigiamas\",\"Agpmpnn\"],[\"teigti\",\"Vgpp-pmpnnnn-p\"],[\"teigiamas\",\"Agpmpvn\"],[\"teigti\",\"Vgpp-pmpnnvn-p\"]],[[\"dalykas\",\"Ncmpnn-\"],[\"dalykas\",\"Ncmpvn-\"]],[[\",\",\"Tc\"]],[[\"tačiau\",\"Cg\"]],[[\"tai\",\"Qg\"],[\"tai\",\"Cg\"],[\"tas\",\"Pgfsdn\"],[\"tai\",\"Pg---n\"],[\"tas\",\"Pgnsnn\"]],[[\"neturėti\",\"Vgm-3---y--ns-\"],[\"neturėti\",\"Vgm-3s--y--ns-\"],[\"neturėti\",\"Vgm-3p--y--ns-\"],[\"neturėti\",\"Vgpa-pmpyngn-p\"],[\"neturėti\",\"Vgpa-pfpyngn-p\"]],[[\"būti\",\"Vgi-----n--n--\"],[\"būti\",\"Vgpa-pmpnnnn-p\"],[\"būti\",\"Vgpa-pmpnnvn-p\"]],[[\"daryti\",\"Vgpp--npnn-n-p\"],[\"daryti\",\"Vgpp-sfpnnnn-p\"],[\"daryti\",\"Vgpp-sfpnnin-p\"],[\"daryti\",\"Vgpp-sfpnnvn-p\"]],[[\"NATO\",\"Ya\"]],[[\"sąskaita\",\"Ncfsin-\"],[\"sąskaita\",\"Ncfsnn-\"],[\"sąskaita\",\"Ncfsvn-\"]],[[\".\",\"Tp\"]],[[\"„\",\"Tu\"]],[[\"kurti\",\"Vgap----n--n--\"]],[[\"šis\",\"Pgfpan\"]],[[\"ES\",\"Ya\"]],[[\"struktūra\",\"Ncfpan-\"]],[[\",\",\"Tc\"]],[[\"svarbus\",\"Agpn--n\"]],[[\"(\",\"Tl\"]],[[\"žiūrėti\",\"Vgi-----n--n--\"],[\"žiūrėti\",\"Vgpa-pmpnnnn-p\"],[\"žiūrėti\",\"Vgpa-pmpnnvn-p\"]],[[\")\",\"Tr\"]],[[\",\",\"Tc\"]],[[\"kad\",\"Cg\"],[\"kad\",\"Qg\"]],[[\"jis\",\"Pgfsgn\"],[\"jis\",\"Pgfpnn\"],[\"joti\",\"Vgmf3s--n--ni-\"],[\"joti\",\"Vgmf3p--n--ni-\"],[\"joti\",\"Vgmf3---n--ni-\"]],[[\"papildyti\",\"Vgm-3s--n--ns-\"],[\"papildyti\",\"Vgm-3p--n--ns-\"],[\"papildyti\",\"Vgm-3---n--ns-\"],[\"papildyti\",\"Vgpa-pmpnngn-p\"],[\"papildyti\",\"Vgpa-pfpnngn-p\"]],[[\"NATO\",\"Ya\"]],[[\",\",\"Tc\"]],[[\"–\",\"Th\"]],[[\"kalbėti\",\"Vgms3s--n--ni-\"],[\"kalbėti\",\"Vgms3p--n--ni-\"],[\"kalbėti\",\"Vgms3---n--ni-\"]],[[\"B.\",\"Ys\"]],[[\"Johnsonas\",\"X-\"]],[[\".\",\"Tp\"]],[[\"–\",\"Th\"]],[[\"nereikėti\",\"Vgm-3s--y--ns-\"],[\"nereikėti\",\"Vgm-3---y--ns-\"],[\"nereikėti\",\"Vgm-3p--y--ns-\"]],[[\"pakenkti\",\"Vgi-----n--n--\"],[\"pakenkti\",\"Vgpa-pmpnnnn-p\"],[\"pakenkti\",\"Vgpa-pmpnnvn-p\"]],[[\"esminis\",\"Agpfsdn\"]],[[\"saugumas\",\"Ncmsgn-\"]],[[\"struktūra\",\"Ncfsdn-\"]],[[\",\",\"Tc\"]],[[\"kuris\",\"Pgfsnn\"],[\"kurti\",\"Vgmp2s--n--ni-\"]],[[\"aš\",\"Pg-pin\"]],[[\"rūpintis\",\"Vgms3s--n--yi-\"],[\"rūpintis\",\"Vgms3p--n--yi-\"],[\"rūpintis\",\"Vgms3---n--yi-\"]],[[\"pastaras\",\"Agpmpay\"]],[[\"70\",\"M----d-\"]],[[\"metai\",\"Ncmpgn-\"]],[[\"“\",\"Tu\"]],[[\".\",\"Tp\"]]],\"stem\":[\"Boris\",\"Johnson\",\":\",\"D.\",\"Trump\",\"yr\",\"ger\",\"prog\",\"Europ\",\"Išrinkt\",\"JAV\",\"prezident\",\"Donald\",\"Trump\",\"yr\",\"žmog\",\",\",\"su\",\"kur\",\"Did\",\"Britanij\",\"ir\",\"Europ\",\"Sąjung\",\"gal\",\"sudarinėt\",\"sandor\",\",\",\"pirmadien\",\"pareišk\",\"Did\",\"Britanij\",\"užsien\",\"reikal\",\"ministr\",\"Boris\",\"Johnson\",\".\",\"„\",\"Donald\",\"Trump\",\",\",\"kaip\",\"jau\",\"sak\",\"ankst\",\",\",\"yr\",\"sandor\",\"sudarinėt\",\",\",\"todėl\",\"man\",\",\",\"kad\",\"tai\",\"gal\",\"būt\",\"ger\",\"Britanij\",\",\",\"taip pat\",\"ger\",\"ir\",\"Europ\",\"“\",\",\",\"–\",\"pareišk\",\"B.\",\"Johnson\",\",\",\"atvykę\",\"į\",\"ES\",\"užsien\",\"reikal\",\"ministr\",\"susitikim\",\",\",\"praleidę\",\"sekmadien\",\"vakar\",\"vykus\",\"ministr\",\"vakarien\",\".\",\"„\",\"Man\",\",\",\"kad\",\"mums\",\"vis\",\"reik\",\"palaukt\",\"ir\",\"pamat\",\",\",\"ką\",\"jie\",\"sugalv\",\",\",\"bet\",\"aš\",\"galvoj\",\",\",\"kad\",\"mes\",\"turėt\",\"tai\",\"vertin\",\"kaip\",\"pasitaikius\",\"prog\",\"“\",\",\",\"–\",\"pridūr\",\"jis\",\".\",\"Netikėt\",\"D.\",\"Trump\",\"pergal\",\"JAV\",\"prezident\",\"rinkim\",\"sukėl\",\"didžiul\",\"nerim\",\"Europ\",\"po\",\"jo\",\"rinkimin\",\"kampanij\",\"pareiškim\",\",\",\"kad\",\"jis\",\"gal\",\"nutraukt\",\"Vašington\",\"įsipareigojim\",\"NATO\",\".\",\"ES\",\"užsien\",\"politik\",\"vadov\",\"Federic\",\"Mogherin\",\"sekmadien\",\"vakar\",\"sureng\",\"neoficial\",\"vakarien\",\",\",\"kur\",\"met\",\"ministr\",\"turėj\",\"apsikeist\",\"nuomon\",\"dėl\",\"JAV\",\"ir\",\"ES\",\"santyk\",\"plėtr\",\"po\",\"rinkim\",\"JAV\",\".\",\"Tač\",\"B.\",\"Johnson\",\"šioje\",\"vakarien\",\"dalyvaut\",\"atsisak\",\",\",\"pareiškę\",\",\",\"kad\",\"tai\",\"bus\",\"blog\",\"ženkl\",\"nauj\",\"išrinkt\",\"JAV\",\"prezident\",\".\",\"Po\",\"sekmadien\",\"susitikim\",\"F.\",\"Mogherin\",\"sak\",\",\",\"kad\",\"ji\",\"tikis\",\"„\",\"lab\",\"tvirt\",\"partneryst\",\"“\",\"su\",\"D\",\".\",\"Trump\",\"administracij\",\",\",\"tač\",\"perspėj\",\",\",\"jog\",\"ES\",\"negal\",\"tiesiog\",\"laukt\",\",\",\"kad\",\"pamatyt\",\",\",\"ką\",\"jis\",\"pasiūl\",\".\",\"„\",\"Š\",\"met\",\"mes\",\"negalim\",\"sau\",\"leist\",\"susitaik\",\"su\",\"„\",\"palauk\",\"ir\",\"pamat\",\"“\",\"požiūr\",\",\",\"nes\",\"pasaul\",\"nestov\",\"viet\",\",\",\"Europ\",\"nestov\",\"viet\",\",\",\"kriz\",\"nestov\",\"viet\",\",\",\"kaip\",\"ir\",\"galimyb\",\",\",\"kur\",\"mes\",\"galim\",\"pasinaudot\",\"“\",\",\",\"–\",\"sak\",\"ji\",\".\",\"F.\",\"Mogherin\",\"yr\",\"parengus\",\"Global\",\"strategij\",\",\",\"kur\",\"turėt\",\"užtikrin\",\"ES\",\"bendr\",\"gynyb\",\"politik\",\",\",\"bet\",\"Britanij\",\"ir\",\"kel\",\"kit\",\"ES\",\"nar\",\"priešinas\",\"jos\",\"plan\",\",\",\"nes\",\"man\",\",\",\"kad\",\"jie\",\"dubliuojas\",\"JAV\",\"vadovaujam\",\"Šiaur\",\"Aljans\",\",\",\"kur\",\"užtikrin\",\"Europ\",\"saugum\",\"nes\",\"1949\",\"met\",\",\",\"strategij\",\".\",\"B.\",\"Johnson\",\"žurnalist\",\"sak\",\",\",\"kad\",\"glaud\",\"ES\",\"bendradarbiavim\",\"gynyb\",\"srit\",\"ir\",\"išlaid\",\"gynyb\",\"didinim\",\"yr\",\"teigiam\",\"dalyk\",\",\",\"tač\",\"tai\",\"neturėt\",\"būt\",\"darom\",\"NATO\",\"sąskait\",\".\",\"„\",\"Kuriant\",\"šias\",\"ES\",\"struktūr\",\",\",\"svarb\",\"(\",\"žiūrėt\",\")\",\",\",\"kad\",\"jos\",\"papildyt\",\"NATO\",\",\",\"–\",\"kalbėj\",\"B.\",\"Johnson\",\".\",\"–\",\"Nereikėt\",\"pakenkt\",\"esmin\",\"saugum\",\"struktūr\",\",\",\"kur\",\"mumis\",\"rūpinos\",\"pastar\",\"70\",\"met\",\"“\",\".\"]}",
            "tags":[
            ]
        },
        {
            "id":1373734,
            "type":"ner",
            "version":10,
            "dateCreated":"2019-11-21T18:19:42.667+02:00",
            "dateModified":"2019-11-21T18:19:42.669+02:00",
            "content":"{\"ne\":{\"money\":[],\"dates\":[{\"text\":\"pirmadienį\",\"ref\":[28,1]},{\"text\":\"sekmadienio vakarą\",\"ref\":[81,2]},{\"text\":\"sekmadienio vakarą\",\"ref\":[151,2]},{\"text\":\"Po sekmadienio\",\"ref\":[193,2]},{\"text\":\"nuo 1949 metų\",\"ref\":[314,3]}],\"products\":[],\"organizations\":[{\"text\":\"Europos Sąjunga\",\"ref\":[22,2]},{\"text\":\"ES\",\"ref\":[74,1]},{\"text\":\"NATO\",\"ref\":[143,1]},{\"text\":\"ES\",\"ref\":[145,1]},{\"text\":\"ES\",\"ref\":[166,1]},{\"text\":\"ES\",\"ref\":[218,1]},{\"text\":\"ES\",\"ref\":[283,1]},{\"text\":\"ES\",\"ref\":[293,1]},{\"text\":\"ES\",\"ref\":[327,1]},{\"text\":\"NATO\",\"ref\":[344,1]},{\"text\":\"ES\",\"ref\":[350,1]},{\"text\":\"NATO\",\"ref\":[361,1]}],\"locations\":[{\"text\":\"Europai\",\"ref\":[8,1]},{\"text\":\"JAV\",\"ref\":[10,1]},{\"text\":\"Didžioji Britanija\",\"ref\":[19,2]},{\"text\":\"Didžiosios Britanijos\",\"ref\":[30,2]},{\"text\":\"Britanijai\",\"ref\":[59,1]},{\"text\":\"Europai\",\"ref\":[64,1]},{\"text\":\"JAV\",\"ref\":[124,1]},{\"text\":\"Europoje\",\"ref\":[130,1]},{\"text\":\"Vašingtono\",\"ref\":[141,1]},{\"text\":\"JAV\",\"ref\":[164,1]},{\"text\":\"JAV\",\"ref\":[171,1]},{\"text\":\"JAV\",\"ref\":[190,1]},{\"text\":\"Europa\",\"ref\":[251,1]},{\"text\":\"Britanija\",\"ref\":[289,1]},{\"text\":\"JAV\",\"ref\":[305,1]},{\"text\":\"Europos\",\"ref\":[312,1]}],\"persons\":[{\"text\":\"Borisas Johnsonas\",\"ref\":[0,2]},{\"text\":\"D. Trumpas\",\"ref\":[3,2]},{\"text\":\"Donaldas Trumpas\",\"ref\":[12,2]},{\"text\":\"Borisas Johnsonas\",\"ref\":[35,2]},{\"text\":\"Donaldas Trumpas\",\"ref\":[39,2]},{\"text\":\"B. Johnsonas\",\"ref\":[69,2]},{\"text\":\"D. Trumpo\",\"ref\":[121,2]},{\"text\":\"Federica Mogherini\",\"ref\":[149,2]},{\"text\":\"B. Johnsonas\",\"ref\":[174,2]},{\"text\":\"F. Mogherini\",\"ref\":[196,2]},{\"text\":\"D.Trumpo\",\"ref\":[209,3]},{\"text\":\"F. Mogherini\",\"ref\":[273,2]},{\"text\":\"B. Johnsonas\",\"ref\":[320,2]},{\"text\":\"B. Johnsonas\",\"ref\":[365,2]}]},\"associations\":{\"dates\":\"sekmadienio vakarą\",\"organizations\":\"ES\",\"locations\":\"JAV\",\"persons\":\"B. Johnsonas\"}}",
            "tags":[
            ]
        }
    ]
}